ggLeap/DataHandler.py
ggLeap/__init__.py
ggLeap/data_aggregation.py
ggLeap/data_collection.py
ggLeap/helpers.py
ggLeap/importing.py
ggLeap/reports.py
ggLeapAnalyticsTools-0.1.0.dist-info/LICENSE
ggLeapAnalyticsTools-0.1.0.dist-info/METADATA
ggLeapAnalyticsTools-0.1.0.dist-info/WHEEL
ggLeapAnalyticsTools-0.1.0.dist-info/top_level.txt
ggLeapAnalyticsTools-0.1.0.dist-info/RECORD
