Metadata-Version: 2.1
Name: ggLeapAnalyticsTools
Version: 0.1.0
Summary: A python package for helping users to generate and interact with data from ggLeap esports venue management software.
Home-page: https://github.com/Phosphorescentt/ggLeapAnalyticsTools
Author: Joshua "Phosphorescent" Mankelow
License: UNKNOWN
Project-URL: Bug Tracker, https://github.com/Phosphorescentt/ggLeapAnalyticsTools/issues
Platform: UNKNOWN
Classifier: Programming Language :: Python :: 3
Classifier: License :: OSI Approved :: GNU Affero General Public License v3 or later (AGPLv3+)
Classifier: Operating System :: OS Independent
Requires-Python: >=3.6
License-File: LICENSE
